aioimdb/__init__.py
aioimdb/auth.py
aioimdb/client.py
aioimdb/constants.py
aioimdb/exceptions.py
aioimdb-1.1.2.dist-info/METADATA
aioimdb-1.1.2.dist-info/RECORD
aioimdb-1.1.2.dist-info/WHEEL
aioimdb-1.1.2.dist-info/top_level.txt
