Metadata-Version: 2.1
Name: aioimdb
Version: 1.1.2
Summary: Python asyncio IMDB client using the IMDB json web service made available for their iOS app.
Home-page: https://github.com/fpierfed/aioimdb
Author: Francesco Pierfederici
Author-email: fpierfed@megabeets.com
License: Creative Commons Attribution-Noncommercial-Share Alike license
Platform: UNKNOWN
Classifier: Development Status :: 5 - Production/Stable
Classifier: Intended Audience :: Developers
Classifier: Operating System :: OS Independent
Classifier: License :: OSI Approved :: Apache Software License
Classifier: Framework :: AsyncIO
Classifier: Programming Language :: Python
Classifier: Programming Language :: Python :: 3.6
Classifier: Topic :: Internet :: WWW/HTTP
Requires-Python: >=3.6
Requires-Dist: wheel (==0.31.0)
Requires-Dist: boto (==2.48.0)
Requires-Dist: python-dateutil (==2.7.2)
Requires-Dist: diskcache (==3.0.1)
Requires-Dist: aiohttp (==3.1.1)
Requires-Dist: setuptools (==39.0.1)
